lxt/__init__.py
lxt/check.py
lxt/core.py
lxt/functional.py
lxt/modules.py
lxt/rules.py
lxt/special.py
lxt/utils.py
lxt/models/__init__.py
lxt/models/bert.py
lxt/models/llama.py
lxt/models/mixtral.py
lxt/models/openclip.py
lxt/models/phi3.py
lxt-0.6.1.dist-info/LICENSE
lxt-0.6.1.dist-info/METADATA
lxt-0.6.1.dist-info/WHEEL
lxt-0.6.1.dist-info/top_level.txt
lxt-0.6.1.dist-info/RECORD
