Metadata-Version: 2.1
Name: lxt
Version: 0.6.1
Summary: LRP explains Transformers
Home-page: https://github.com/rachtibat/LRP-for-Transformers
Author: Reduan Achtibat
License: BSD 3-clause
License-File: LICENSE
Requires-Dist: torch
Requires-Dist: transformers >=4.46.2
Requires-Dist: accelerate
Requires-Dist: tabulate
Requires-Dist: matplotlib
Requires-Dist: bitsandbytes
Requires-Dist: open-clip-torch
